notte_agent/README.md
notte_agent/__init__.py
notte_agent/agent.py
notte_agent/agent_fallback.py
notte_agent/errors.py
notte_agent/main.py
notte_agent/py.typed
notte_agent/workflow.py
notte_agent/common/__init__.py
notte_agent/common/base.py
notte_agent/common/conversation.py
notte_agent/common/notifier.py
notte_agent/common/parser.py
notte_agent/common/perception.py
notte_agent/common/prompt.py
notte_agent/common/types.py
notte_agent/common/validator.py
notte_agent/falco/__init__.py
notte_agent/falco/agent.py
notte_agent/falco/perception.py
notte_agent/falco/prompt.py
notte_agent/falco/system.md
notte_agent/gufo/__init__.py
notte_agent/gufo/agent.py
notte_agent/gufo/perception.py
notte_agent/gufo/prompt.py
notte_agent/gufo/system.md
notte_agent-1.8.3.dist-info/METADATA
notte_agent-1.8.3.dist-info/WHEEL
notte_agent-1.8.3.dist-info/RECORD
