Metadata-Version: 2.4
Name: notte-agent
Version: 1.8.3
Summary: Notte Web AI Agents
Author-email: Notte Team  <hello@notte.cc>
Requires-Python: >=3.11
Requires-Dist: notte-browser==v1.8.3
Requires-Dist: notte-core==v1.8.3
Requires-Dist: notte-llm==v1.8.3
